{
  "type": "crockpot:crock_pot_cooking",
  "requirements": [
    {
      "type": "category_min",
      "category": "FISH",
      "min": 2.0
    },
    {
      "type": "category_min_exclusive",
      "category": "FROZEN",
      "min": 0.0
    },
    {
      "type": "category_max",
      "category": "INEDIBLE",
      "max": 0.0
    },
    {
      "type": "category_max",
      "category": "EGG",
      "max": 0.0
    }
  ],
  "result": "crockpot:ceviche",
  "priority": 20,
  "cookingtime": 200,
  "potlevel": 2
}