{
  "type": "crockpot:crock_pot_cooking",
  "cookingtime": 400,
  "potlevel": 0,
  "priority": 1,
  "requirements": [
    {
      "type": "CATEGORY_MIN",
      "category": "EGG",
      "min": 1.0
    },
    {
      "type": "CATEGORY_MIN",
      "category": "VEGGIE",
      "min": 1.0
    },
    {
      "type": "CATEGORY_MAX",
      "category": "MEAT",
      "max": 0.0
    },
    {
      "type": "CATEGORY_MAX",
      "category": "DAIRY",
      "max": 0.0
    }
  ],
  "result": "crockpot:breakfast_skillet"
}